whooper/__init__.py
whooper/_boto.py
whooper/_redshift.py
whooper/_s3.py
whooper-0.0.1.dist-info/LICENSE
whooper-0.0.1.dist-info/WHEEL
whooper-0.0.1.dist-info/METADATA
whooper-0.0.1.dist-info/RECORD
