Metadata-Version: 2.1
Name: whooper
Version: 0.0.1
Summary: Convenience wrappers for connecting to AWS S3 and Redshift
Home-page: https://github.com/nickbuker/whooper
License: UNKNOWN
Author: Nick Buker
Author-email: nickbuker@gmail.com
Requires-Python: >=3.6,<4
Classifier: Development Status :: 3 - Alpha
Classifier: License :: OSI Approved :: Apache Software License
Classifier: Programming Language :: Python :: 3.6
Classifier: Programming Language :: Python :: 3.7
Classifier: Programming Language :: Python :: 3.8
Classifier: Programming Language :: Python :: 3.9
Requires-Dist: boto3 >=1.17.11
Requires-Dist: pg8000 >=1.17.0
